nifty_ls-1.1.0.dist-info/RECORD
nifty_ls-1.1.0.dist-info/WHEEL
nifty_ls-1.1.0.dist-info/METADATA
nifty_ls-1.1.0.dist-info/licenses/LICENSE
nifty_ls/cufinufft.py
nifty_ls/astropy.py
nifty_ls/chi2_helpers.abi3.so
nifty_ls/version.py
nifty_ls/cpu_helpers.cpp
nifty_ls/__init__.py
nifty_ls/core.py
nifty_ls/finufft.py
nifty_ls/cpu_helpers.hpp
nifty_ls/backends.py
nifty_ls/cpu_helpers.abi3.so
nifty_ls/utils.py
nifty_ls/finufft_chi2.py
nifty_ls/cufinufft_chi2.py
nifty_ls/chi2_helpers.cpp
nifty_ls/.dylibs/libomp.dylib
nifty_ls/test_helpers/utils.py
