Metadata-Version: 2.1
Name: nifty-ls
Version: 1.1.0
Summary: A fast Lomb-Scargle periodogram. It's nifty, and uses a NUFFT.
Author: Lehman Garrison, Dan Foreman-Mackey, Yuwei (Peter) Sun
License:                                  Apache License
Project-URL: Homepage, https://github.com/flatironinstitute.org/nifty-ls
Requires-Python: >=3.9
Requires-Dist: numpy
Requires-Dist: finufft>=2.3
Provides-Extra: cuda11
Requires-Dist: cufinufft; extra == "cuda11"
Requires-Dist: cupy-cuda11x; extra == "cuda11"
Provides-Extra: cuda12
Requires-Dist: cufinufft; extra == "cuda12"
Requires-Dist: cupy-cuda12x; extra == "cuda12"
Provides-Extra: cuda
Requires-Dist: cufinufft; extra == "cuda"
Requires-Dist: cupy-cuda12x; extra == "cuda"
